README.rst
setup.cfg
setup.py
lib/icehashpassword.py
lib/zeroc_icehashpassword.egg-info/PKG-INFO
lib/zeroc_icehashpassword.egg-info/SOURCES.txt
lib/zeroc_icehashpassword.egg-info/dependency_links.txt
lib/zeroc_icehashpassword.egg-info/entry_points.txt
lib/zeroc_icehashpassword.egg-info/requires.txt
lib/zeroc_icehashpassword.egg-info/top_level.txt