Metadata-Version: 1.1
Name: zeroc-icehashpassword
Version: 1.0.2
Summary: ZeroC Ice hash password utility
Home-page: https://github.com/zeroc-ice/ice
Author: ZeroC, Inc.
Author-email: info@zeroc.com
License: BSD
Download-URL: https://github.com/zeroc-ice/ice/archive/v1.0.2-icehashpassword.tar.gz
Keywords: ice,hash,password
Platform: UNKNOWN
Classifier: Development Status :: 5 - Production/Stable
Classifier: Intended Audience :: Developers
Classifier: Topic :: Security
Classifier: Topic :: Software Development :: Libraries :: Python Modules
Classifier: Operating System :: OS Independent
Classifier: License :: OSI Approved :: BSD License
Classifier: Programming Language :: Python :: 2
Classifier: Programming Language :: Python :: 2.6
Classifier: Programming Language :: Python :: 2.7
Classifier: Programming Language :: Python :: 3
Classifier: Programming Language :: Python :: 3.0
Classifier: Programming Language :: Python :: 3.1
Classifier: Programming Language :: Python :: 3.2
Classifier: Programming Language :: Python :: 3.3
Classifier: Programming Language :: Python :: 3.4
